MANIFEST.in
README
setup.py
django_snapshot.egg-info/PKG-INFO
django_snapshot.egg-info/SOURCES.txt
django_snapshot.egg-info/dependency_links.txt
django_snapshot.egg-info/not-zip-safe
django_snapshot.egg-info/top_level.txt
snapshot/__init__.py
snapshot/models.py
snapshot/settings.py
snapshot/tests.py
snapshot/utils.py
snapshot/views.py
snapshot/management/__init__.py
snapshot/management/commands/__init__.py
snapshot/management/commands/snap.py